markitup/__about__.py
markitup/__init__.py
markitup/__main__.py
markitup/_base_converter.py
markitup/_exceptions.py
markitup/_markitup.py
markitup/_schemas.py
markitup/_uri_utils.py
markitup/py.typed
markitup/converter_utils/__init__.py
markitup/converter_utils/utils.py
markitup/converter_utils/docx/__init__.py
markitup/converter_utils/docx/pre_process.py
markitup/converter_utils/docx/math/__init__.py
markitup/converter_utils/docx/math/latex_dict.py
markitup/converter_utils/docx/math/omml.py
markitup/converters/__init__.py
markitup/converters/_audio_converter.py
markitup/converters/_csv_converter.py
markitup/converters/_docx_converter.py
markitup/converters/_exiftool.py
markitup/converters/_html_converter.py
markitup/converters/_image_converter.py
markitup/converters/_markdownify.py
markitup/converters/_pdf_converter.py
markitup/converters/_plain_text_converter.py
markitup/converters/_pptx_converter.py
markitup/converters/_xlsx_converter.py
pathintegral_markitup-0.1.1.dist-info/METADATA
pathintegral_markitup-0.1.1.dist-info/WHEEL
pathintegral_markitup-0.1.1.dist-info/entry_points.txt
pathintegral_markitup-0.1.1.dist-info/RECORD
