Metadata-Version: 2.4
Name: pathintegral-markitup
Version: 0.1.1
Summary: Utility tool for converting various files to Markdown
Author: Path Integral Institute
License-Expression: MIT
Classifier: Development Status :: 4 - Beta
Classifier: Programming Language :: Python
Classifier: Programming Language :: Python :: 3.10
Classifier: Programming Language :: Python :: 3.11
Classifier: Programming Language :: Python :: 3.12
Classifier: Programming Language :: Python :: 3.13
Classifier: Programming Language :: Python :: Implementation :: CPython
Classifier: Programming Language :: Python :: Implementation :: PyPy
Requires-Python: >=3.10
Requires-Dist: beautifulsoup4
Requires-Dist: charset-normalizer
Requires-Dist: filetype>=1.2.0
Requires-Dist: langchain-text-splitters>=0.3.8
Requires-Dist: lxml
Requires-Dist: mammoth
Requires-Dist: markdownify
Requires-Dist: olefile
Requires-Dist: openpyxl>=3.1.5
Requires-Dist: pandas
Requires-Dist: pydantic>=2.0.0
Requires-Dist: pymupdf4llm>=0.0.21
Requires-Dist: pymupdf>=1.25.5
Requires-Dist: python-pptx
Requires-Dist: requests
Requires-Dist: speechrecognition
Requires-Dist: tiktoken>=0.9.0
Requires-Dist: xlrd>=2.0.1
Provides-Extra: all
Requires-Dist: pydub; extra == 'all'
Requires-Dist: python-magic>=0.4.27; extra == 'all'
Provides-Extra: audio
Requires-Dist: pydub; extra == 'audio'
Provides-Extra: magic
Requires-Dist: python-magic>=0.4.27; extra == 'magic'
